attrs_marshmallow/__init__.py
attrs_marshmallow/fields/__init__.py
attrs_marshmallow/fields/enum.py
attrs_marshmallow/fields/nested.py
attrs_marshmallow/fields/path.py
attrs_marshmallow/fields/polymorphic.py
attrs_marshmallow-0.6.2.dist-info/WHEEL
attrs_marshmallow-0.6.2.dist-info/METADATA
attrs_marshmallow-0.6.2.dist-info/RECORD
