Metadata-Version: 2.1
Name: attrs-marshmallow
Version: 0.6.2
Summary: 
Keywords: marshmallow,attrs,serialization,deserialization
Author: Igor Stuzhuk (KoHcoJlb)
Author-email: fujitsuigor@gmail.com
Requires-Python: >=3.7,<4.0
Classifier: Programming Language :: Python :: 3
Classifier: Programming Language :: Python :: 3.7
Classifier: Programming Language :: Python :: 3.8
Classifier: Programming Language :: Python :: 3.9
Requires-Dist: attrs (>=19.1,<20.0)
Requires-Dist: marshmallow (>=3.0)
Requires-Dist: typing-inspect (>=0.5.0,<0.6.0)
Project-URL: Repository, https://github.com/KoHcoJlb/attrs-marshmallow
